LICENSE
NOTICE
README.md
setup.py
spdlayers/__init__.py
spdlayers/layers.py
spdlayers/tools.py
spdlayers/version.py
spdlayers.egg-info/PKG-INFO
spdlayers.egg-info/SOURCES.txt
spdlayers.egg-info/dependency_links.txt
spdlayers.egg-info/requires.txt
spdlayers.egg-info/top_level.txt