Metadata-Version: 2.1
Name: spdlayers
Version: 0.2.0
Summary: Symmetric Positive Definite (SPD) enforcement layers for PyTorch
Home-page: https://github.com/LLNL/spdlayers
Author: Charles Jekel
Author-email: jekel1@llnl.gov
License: MIT License
Platform: any
Classifier: License :: OSI Approved :: MIT License
Classifier: Programming Language :: Python :: 3
Requires-Python: >=3.6
License-File: LICENSE
License-File: NOTICE
